ordered_utils.py
ordered_set_custom-0.3.dist-info/METADATA
ordered_set_custom-0.3.dist-info/WHEEL
ordered_set_custom-0.3.dist-info/top_level.txt
ordered_set_custom-0.3.dist-info/RECORD
