Metadata-Version: 2.4
Name: ordered-set-custom
Version: 0.3
Summary: A utility to create ordered sets from iterables
Home-page: https://github.com/PriyanshuSingh44/ordered-set-custom
Author: Priyanshu Singh
Author-email: your_email@example.com
Project-URL: Source, https://github.com/PriyanshuSingh44/ordered-set-custom
Project-URL: Tracker, https://github.com/PriyanshuSingh44/ordered-set-custom/issues
Classifier: Programming Language :: Python :: 3
Classifier: License :: OSI Approved :: MIT License
Requires-Python: >=3.6
Dynamic: author
Dynamic: author-email
Dynamic: classifier
Dynamic: description
Dynamic: description-content-type
Dynamic: home-page
Dynamic: project-url
Dynamic: requires-python
Dynamic: summary
